README.rst
setup.py
MatPlotTheme.egg-info/PKG-INFO
MatPlotTheme.egg-info/SOURCES.txt
MatPlotTheme.egg-info/dependency_links.txt
MatPlotTheme.egg-info/requires.txt
MatPlotTheme.egg-info/top_level.txt
matplottheme/__init__.py
matplottheme/palette/__init__.py
matplottheme/palette/default.py
matplottheme/palette/ggplot2.py
matplottheme/style/__init__.py
matplottheme/style/default.py
matplottheme/style/ggplot2.py
matplottheme/tests/__init__.py
matplottheme/tests/bar.py
matplottheme/tests/boxplot.py
matplottheme/tests/fill.py
matplottheme/tests/hist.py
matplottheme/tests/pcolormesh.py
matplottheme/tests/plot.py
matplottheme/tests/scatter.py
matplottheme/tests/summary.py
matplottheme/tests/baseline_images/bar/bar1.png
matplottheme/tests/baseline_images/bar/bar2.png
matplottheme/tests/baseline_images/boxplot/boxplot1.png
matplottheme/tests/baseline_images/boxplot/boxplot2.png
matplottheme/tests/baseline_images/fill/fill1.png
matplottheme/tests/baseline_images/fill/fill2.png
matplottheme/tests/baseline_images/hist/hist1.png
matplottheme/tests/baseline_images/hist/hist2.png
matplottheme/tests/baseline_images/pcolormesh/pcolormesh1.png
matplottheme/tests/baseline_images/pcolormesh/pcolormesh2.png
matplottheme/tests/baseline_images/pcolormesh/pcolormesh3.png
matplottheme/tests/baseline_images/pcolormesh/pcolormesh4.png
matplottheme/tests/baseline_images/plot/plot1.png
matplottheme/tests/baseline_images/scatter/scatter1.png
matplottheme/tests/baseline_images/summary/default.png
matplottheme/tests/baseline_images/summary/ggplot2.png