Metadata-Version: 1.1
Name: MatPlotTheme
Version: 0.1.0
Summary: MatPlotTheme is a theming library for MatPlotLib.
Home-page: https://github.com/James-Yu/MatPlotTheme
Author: James Yu
Author-email: jqyu@eee.hku.hk
License: MIT License
Platform: UNKNOWN
Classifier: Development Status :: 3 - Alpha
Classifier: Intended Audience :: Science/Research
Classifier: License :: OSI Approved :: MIT License
Classifier: Operating System :: OS Independent
Classifier: Programming Language :: Python :: 2.7
Classifier: Programming Language :: Python :: 3.3
Classifier: Programming Language :: Python :: 3.4
Classifier: Topic :: Scientific/Engineering
